Calibrator_KS1200/.gitignore
Calibrator_KS1200/Exchange_data_str_bu7.py
Calibrator_KS1200/Exchange_data_str_itm.py
Calibrator_KS1200/Ks1200.desktop
Calibrator_KS1200/Logo_etalon.ico
Calibrator_KS1200/Logo_etalon.png
Calibrator_KS1200/__init__.py
Calibrator_KS1200/func_lib.py
Calibrator_KS1200/ks1200.db
Calibrator_KS1200/ks1200.py
Calibrator_KS1200/templates/Protocol_calibration_TP.docx
Calibrator_KS1200/templates/Protocol_graduation_TS.docx
Calibrator_KS1200/templates/Protocol_verification_TP.docx
Calibrator_KS1200/templates/Protocol_verification_TS.docx
calibrator_ks1200-0.4.dist-info/METADATA
calibrator_ks1200-0.4.dist-info/WHEEL
calibrator_ks1200-0.4.dist-info/top_level.txt
calibrator_ks1200-0.4.dist-info/RECORD
