Metadata-Version: 2.4
Name: Calibrator-KS1200
Version: 0.4
Summary: Package for calibrator dry block KS-1200-1
Author-email: Denis Nikolaev <nickolaev.d@gmail.com>
License: BSD-3-Clause
Classifier: Programming Language :: Python :: 3
Classifier: License :: OSI Approved :: MIT License
Classifier: Operating System :: OS Independent
Requires-Python: >=3.5
Requires-Dist: PyQt5
Requires-Dist: numpy
Requires-Dist: pyqtgraph
Requires-Dist: pyserial
Requires-Dist: python-docx
